bor2diggs/__init__.py
bor2diggs/cli.py
bor2diggs/convert.py
bor2diggs-0.1.2.dist-info/entry_points.txt
bor2diggs-0.1.2.dist-info/LICENSE
bor2diggs-0.1.2.dist-info/WHEEL
bor2diggs-0.1.2.dist-info/METADATA
bor2diggs-0.1.2.dist-info/RECORD
