Metadata-Version: 2.3
Name: bor2diggs
Version: 0.1.2
Summary: Convert BOR files to DIGGS
Author-email: Salem Harrache <dev@mail.lim.eu>
Requires-Python: >=3.9
Classifier: Development Status :: 2 - Pre-Alpha
Classifier: License :: OSI Approved :: MIT License
Classifier: Programming Language :: Python :: 3
Classifier: Programming Language :: Python :: 3.9
Classifier: Programming Language :: Python :: 3.10
Classifier: Programming Language :: Python :: 3.11
Classifier: Programming Language :: Python :: 3.12
Requires-Dist: borfile
Requires-Dist: click
Requires-Dist: pint
Requires-Dist: black ; extra == "dev"
Requires-Dist: bump-my-version ; extra == "dev"
Requires-Dist: ruff ; extra == "dev"
Requires-Dist: isort ; extra == "dev"
Requires-Dist: jedi ; extra == "dev"
Requires-Dist: pdbpp ; extra == "dev"
Requires-Dist: coverage ; extra == "test"
Requires-Dist: pytest ; extra == "test"
Requires-Dist: pytest-cases ; extra == "test"
Requires-Dist: pytest-datafiles ; extra == "test"
Requires-Dist: pytest-sugar ; extra == "test"
Project-URL: Changes, https://github.com/LIMSAS/bor2diggs/blob/master/CHANGES.rst
Project-URL: Home, https://bor-form.at
Project-URL: Source, https://github.com/LIMSAS/bor2diggs
Provides-Extra: dev
Provides-Extra: test
